deepscratch/__init__.py
deepscratch/activations.py
deepscratch/layers.py
deepscratch/losses.py
deepscratch/optimizer.py
deepscratch/sequential.py
deepscratch/__pycache__/__init__.cpython-37.pyc
deepscratch/__pycache__/activations.cpython-37.pyc
deepscratch/__pycache__/layers.cpython-37.pyc
deepscratch/__pycache__/losses.cpython-37.pyc
deepscratch/__pycache__/optimizer.cpython-37.pyc
deepscratch/__pycache__/sequential.cpython-37.pyc
deepscratch/layers/__init__.py
deepscratch/layers/activation_layers.py
deepscratch/layers/layers.py
deepscratch-0.0.4.dist-info/LICENSE
deepscratch-0.0.4.dist-info/METADATA
deepscratch-0.0.4.dist-info/WHEEL
deepscratch-0.0.4.dist-info/top_level.txt
deepscratch-0.0.4.dist-info/RECORD
